__init__.py
test.py
PyGraphing/__init__.py
PyGraphing/frame.py
PyGraphing/graph.py
PyGraphing/icon.py
PyGraphing/legend.py
PyGraphing/plot.py
PyGraphing/data_sturctures/PriorityQueue.py
PyGraphing/data_sturctures/UnionFind.py
PyGraphing/data_sturctures/__init__.py
PyGraphing/data_sturctures/tree.py
PyGraphing/series/__init__.py
PyGraphing/series/pie.py
PyGraphing/series/series.py
PyGraphing/series/scatter/__init__.py
PyGraphing/series/scatter/curve.py
PyGraphing/series/scatter/error.py
PyGraphing/series/scatter/errorB.py
PyGraphing/series/scatter/errorT.py
PyGraphing/series/scatter/grouped.py
PyGraphing/series/scatter/line.py
PyGraphing/series/scatter/plot_rect.py
PyGraphing/series/scatter/scatter.py
PyGraphing-1.0.3.dist-info/LICENSE
PyGraphing-1.0.3.dist-info/METADATA
PyGraphing-1.0.3.dist-info/WHEEL
PyGraphing-1.0.3.dist-info/top_level.txt
PyGraphing-1.0.3.dist-info/RECORD
