Metadata-Version: 2.2
Name: PyGraphing
Version: 1.0.3
Summary: Python interface for creating SVG Graphs
Author-email: Carter Bodinger <carterallenbodinger@yahoo.com>
License:                     GNU GENERAL PUBLIC LICENSE
Classifier: Programming Language :: Python :: 3
Classifier: License :: OSI Approved :: GNU General Public License v2 (GPLv2)
Classifier: Operating System :: OS Independent
Requires-Python: >=3.7
License-File: LICENSE
